ronchipy/__init__.py
ronchipy/aberations/__init__.py
ronchipy/aberations/aberations.py
ronchipy/utils/__init__.py
ronchipy/utils/utils.py
ronchipy-0.0.23.dist-info/METADATA
ronchipy-0.0.23.dist-info/WHEEL
ronchipy-0.0.23.dist-info/licenses/LICENSE
ronchipy-0.0.23.dist-info/RECORD
