Metadata-Version: 2.1
Name: ronchipy
Version: 0.0.23
Summary: A package to generate electron Ronchigrams
Project-URL: Homepage, https://github.com/alex-rakowski/ronchipy
Project-URL: Issues, https://github.com/alex-rakowski/ronchipy/issues
Author: Alex Rakowski
License-File: LICENSE
Classifier: Development Status :: 2 - Pre-Alpha
Classifier: Intended Audience :: Education
Classifier: Intended Audience :: Science/Research
Classifier: License :: OSI Approved :: MIT License
Classifier: Operating System :: OS Independent
Classifier: Programming Language :: Python :: 3 :: Only
Classifier: Programming Language :: Python :: 3.9
Classifier: Programming Language :: Python :: 3.10
Classifier: Programming Language :: Python :: 3.11
Classifier: Programming Language :: Python :: 3.12
Classifier: Programming Language :: Python :: Implementation :: CPython
Classifier: Topic :: Scientific/Engineering :: Artificial Intelligence
Classifier: Topic :: Scientific/Engineering :: Physics
Requires-Python: >=3.9
Requires-Dist: matplotlib
Requires-Dist: numpy
Requires-Dist: scipy>=1.11.2
Provides-Extra: dev
Requires-Dist: black; extra == 'dev'
Requires-Dist: pre-commit; extra == 'dev'
Requires-Dist: pytest; extra == 'dev'
Requires-Dist: pytest-cov; extra == 'dev'
Requires-Dist: ruff; extra == 'dev'
Requires-Dist: torch>2.1; extra == 'dev'
Requires-Dist: torchdict; extra == 'dev'
Provides-Extra: testing
Requires-Dist: pytest; extra == 'testing'
Requires-Dist: pytest-cov; extra == 'testing'
Provides-Extra: torch
Requires-Dist: torch>=2.1; extra == 'torch'
Requires-Dist: torchdict; extra == 'torch'
